<annotation verified="yes">
	<folder>Evac-Final-Images</folder>
	<filename>evac2450.jpg</filename>
	<path>/home/rohan/Documents/RCJ2021Repos/raspberry-pi-images-rcj/Evac-Train-Jpgs/evac2450.jpg</path>
	<source>
		<database>Unknown</database>
	</source>
	<size>
		<width>300</width>
		<height>300</height>
		<depth>3</depth>
	</size>
	<segmented>0</segmented>
	<object>
		<name>dead_ball</name>
		<pose>Unspecified</pose>
		<truncated>0</truncated>
		<difficult>0</difficult>
		<bndbox>
			<xmin>28</xmin>
			<ymin>41</ymin>
			<xmax>80</xmax>
			<ymax>94</ymax>
		</bndbox>
	</object>
	<object>
		<name>dead_ball</name>
		<pose>Unspecified</pose>
		<truncated>0</truncated>
		<difficult>0</difficult>
		<bndbox>
			<xmin>93</xmin>
			<ymin>35</ymin>
			<xmax>170</xmax>
			<ymax>113</ymax>
		</bndbox>
	</object>
	<object>
		<name>alive_ball</name>
		<pose>Unspecified</pose>
		<truncated>1</truncated>
		<difficult>0</difficult>
		<bndbox>
			<xmin>165</xmin>
			<ymin>57</ymin>
			<xmax>300</xmax>
			<ymax>195</ymax>
		</bndbox>
	</object>
	<object>
		<name>alive_ball</name>
		<pose>Unspecified</pose>
		<truncated>1</truncated>
		<difficult>0</difficult>
		<bndbox>
			<xmin>248</xmin>
			<ymin>34</ymin>
			<xmax>300</xmax>
			<ymax>121</ymax>
		</bndbox>
	</object>
</annotation>