<annotation verified="yes">
	<folder>Final-Images</folder>
	<filename>line198.jpg</filename>
	<path>/home/rohan/Documents/RCJ2021Repos/raspberry-pi-images-rcj/Line/Train-Jpgs/line198.jpg</path>
	<source>
		<database>Unknown</database>
	</source>
	<size>
		<width>300</width>
		<height>300</height>
		<depth>3</depth>
	</size>
	<segmented>0</segmented>
	<object>
		<name>bottom_right</name>
		<pose>Unspecified</pose>
		<truncated>1</truncated>
		<difficult>0</difficult>
		<bndbox>
			<xmin>151</xmin>
			<ymin>192</ymin>
			<xmax>300</xmax>
			<ymax>299</ymax>
		</bndbox>
	</object>
	<object>
		<name>bottom_right</name>
		<pose>Unspecified</pose>
		<truncated>1</truncated>
		<difficult>0</difficult>
		<bndbox>
			<xmin>1</xmin>
			<ymin>45</ymin>
			<xmax>33</xmax>
			<ymax>90</ymax>
		</bndbox>
	</object>
	<object>
		<name>bottom_right</name>
		<pose>Unspecified</pose>
		<truncated>1</truncated>
		<difficult>0</difficult>
		<bndbox>
			<xmin>147</xmin>
			<ymin>1</ymin>
			<xmax>218</xmax>
			<ymax>16</ymax>
		</bndbox>
	</object>
	<object>
		<name>top_left</name>
		<pose>Unspecified</pose>
		<truncated>0</truncated>
		<difficult>0</difficult>
		<bndbox>
			<xmin>98</xmin>
			<ymin>27</ymin>
			<xmax>182</xmax>
			<ymax>63</ymax>
		</bndbox>
	</object>
	<object>
		<name>top_left</name>
		<pose>Unspecified</pose>
		<truncated>0</truncated>
		<difficult>0</difficult>
		<bndbox>
			<xmin>59</xmin>
			<ymin>132</ymin>
			<xmax>204</xmax>
			<ymax>249</ymax>
		</bndbox>
	</object>
</annotation>