<annotation verified="yes">
	<folder>Final-Images</folder>
	<filename>line797.jpg</filename>
	<path>/home/rohan/Documents/RCJ2021Repos/raspberry-pi-images-rcj/Line/Train-Jpgs/line797.jpg</path>
	<source>
		<database>Unknown</database>
	</source>
	<size>
		<width>300</width>
		<height>300</height>
		<depth>3</depth>
	</size>
	<segmented>0</segmented>
	<object>
		<name>bottom_left</name>
		<pose>Unspecified</pose>
		<truncated>0</truncated>
		<difficult>0</difficult>
		<bndbox>
			<xmin>51</xmin>
			<ymin>32</ymin>
			<xmax>141</xmax>
			<ymax>67</ymax>
		</bndbox>
	</object>
	<object>
		<name>bottom_right</name>
		<pose>Unspecified</pose>
		<truncated>0</truncated>
		<difficult>0</difficult>
		<bndbox>
			<xmin>110</xmin>
			<ymin>27</ymin>
			<xmax>206</xmax>
			<ymax>60</ymax>
		</bndbox>
	</object>
	<object>
		<name>top_right</name>
		<pose>Unspecified</pose>
		<truncated>0</truncated>
		<difficult>0</difficult>
		<bndbox>
			<xmin>100</xmin>
			<ymin>10</ymin>
			<xmax>176</xmax>
			<ymax>34</ymax>
		</bndbox>
	</object>
</annotation>